{
  "flink_flips": {
    "status": "error",
    "reason": "404 Client Error: Not Found for url: https://api.github.com/repos/apache/flink/contents/flink-docs/docs/flips"
  },
  "mcp_spec": {
    "status": "ok",
    "tag_name": "2025-11-25",
    "published_at": "2025-11-25T21:17:42Z",
    "html_url": "https://github.com/modelcontextprotocol/modelcontextprotocol/releases/tag/2025-11-25",
    "checked_at": "2026-04-18T12:09:26.251559"
  },
  "a2a_spec": {
    "status": "ok",
    "tag_name": "v1.0.0",
    "published_at": "2026-03-12T16:34:41Z",
    "html_url": "https://github.com/a2aproject/A2A/releases/tag/v1.0.0",
    "checked_at": "2026-04-18T12:09:28.011390"
  },
  "nist_ai_rmf": {
    "status": "skipped",
    "reason": "feedparser not installed"
  },
  "nist_nccoe": {
    "status": "error",
    "reason": "403 Client Error: Forbidden for url: https://www.nccoe.nist.gov/projects/software-and-ai-agent-identity"
  }
}